flask_jwe
